pqca/__init__.py
pqca/automaton.py
pqca/backend.py
pqca/exceptions.py
pqca/tessellation.py
pqca/update_frame.py
pqca/vector.py
pqca-2.0.0.dist-info/METADATA
pqca-2.0.0.dist-info/WHEEL
pqca-2.0.0.dist-info/top_level.txt
pqca-2.0.0.dist-info/RECORD
