Metadata-Version: 2.2
Name: pqca
Version: 2.0.0
Summary: Construct and simulate partitioned quantum cellular automata
Home-page: https://github.com/hmillerbakewell/partitioned-quantum-cellular-automata
Author: Hector Miller-Bakewell
Author-email: hmillerbakewell@gmail.com
Keywords: quantum computing,cellular automata
Classifier: Programming Language :: Python :: 3
Classifier: Programming Language :: Python :: 3.8
Classifier: License :: OSI Approved :: MIT License
Classifier: Operating System :: OS Independent
Requires-Python: >=3.8
Requires-Dist: qiskit>=1.0
Requires-Dist: qiskit_ibm_runtime>=0.35
Requires-Dist: qiskit_aer
